CHANGELOG.txt
LICENSE.txt
MANIFEST.in
README.txt
scratch.py
setup.py
TOPSIS_Arsh_101803614.egg-info/PKG-INFO
TOPSIS_Arsh_101803614.egg-info/SOURCES.txt
TOPSIS_Arsh_101803614.egg-info/dependency_links.txt
TOPSIS_Arsh_101803614.egg-info/entry_points.txt
TOPSIS_Arsh_101803614.egg-info/requires.txt
TOPSIS_Arsh_101803614.egg-info/top_level.txt