Metadata-Version: 2.1
Name: TOPSIS-Arsh-101803614
Version: 0.0.1
Summary: This Python Package is used to implement the TOPSIS Algorithm
Home-page: UNKNOWN
Author: Arsh Mittal
Author-email: amittal2_be18@thapar.edu
License: MIT
Keywords: TOPSIS
Platform: UNKNOWN
Classifier: Development Status :: 5 - Production/Stable
Classifier: Intended Audience :: Education
Classifier: Operating System :: Microsoft :: Windows :: Windows 10
Classifier: License :: OSI Approved :: MIT License
Classifier: Programming Language :: Python :: 3
